odoo/addons/shopinvader_contact_address_default/README.rst
odoo/addons/shopinvader_contact_address_default/__init__.py
odoo/addons/shopinvader_contact_address_default/__manifest__.py
odoo/addons/shopinvader_contact_address_default/i18n/shopinvader_contact_address_default.pot
odoo/addons/shopinvader_contact_address_default/readme/CONTRIBUTORS.rst
odoo/addons/shopinvader_contact_address_default/readme/DESCRIPTION.rst
odoo/addons/shopinvader_contact_address_default/services/__init__.py
odoo/addons/shopinvader_contact_address_default/services/address.py
odoo/addons/shopinvader_contact_address_default/static/description/index.html
odoo/addons/shopinvader_contact_address_default/tests/__init__.py
odoo/addons/shopinvader_contact_address_default/tests/test_address.py
odoo14_addon_shopinvader_contact_address_default-14.0.1.0.1.dev3.dist-info/METADATA
odoo14_addon_shopinvader_contact_address_default-14.0.1.0.1.dev3.dist-info/WHEEL
odoo14_addon_shopinvader_contact_address_default-14.0.1.0.1.dev3.dist-info/top_level.txt
odoo14_addon_shopinvader_contact_address_default-14.0.1.0.1.dev3.dist-info/RECORD
